Workbook

Sheet README
A1: Summit Outfitters FP&A Model (simulated data)
A3: Purpose: FY2026 budget vs. actual variance analysis and a 12-month rolling forecast with scenarios.
A4: Data: simulated monthly P&L for a fictional specialty retailer; margins calibrated to public big-box retail peers.
A5: Actuals run through Sep 2026. Oct 2026 onward is forecast.
A7: Sheets
A8: Assumptions: scenario selector and forecast drivers. Blue = input, yellow = key assumption you can change.
A9: Data: monthly budget and actual by P&L line (source: data/pl_monthly.csv, summed across regions and channels).
A10: Budget vs Actual: FY2026 by month with variance $ and %, YTD and full-year latest estimate.
A11: Forecast: Oct 2026 - Sep 2027 P&L driven by the selected scenario.
A13: Sign convention: revenue positive, costs negative, so variance = actual - budget is favorable when positive.
A14: Base revenue forecast: log-linear trend + month-of-year model fitted per region x channel in analysis.py (backtest MAPE 1.51% on Jan-Sep 2026).

Sheet Assumptions
A1: Forecast assumptions
A3: Selected scenario | B3: Base | C3: Choose Base, Upside or Downside
A5: Scenario | B5: Revenue multiplier | C5: Gross margin adj. (pts)
A6: Base | B6: 1 | C6: 0
A7: Upside | B7: 1.03 | C7: 0.005
A8: Downside | B8: 0.95 | C8: -0.01
A10: Active revenue multiplier | B10: =INDEX($B$6:$B$8,MATCH($B$3,$A$6:$A$8,0)) -> 1
A11: Active gross margin adj. | B11: =INDEX($C$6:$C$8,MATCH($B$3,$A$6:$A$8,0)) -> 0
A12: Gross margin, trailing 12 months | B12: 0.37696842 | C12: Source: actuals Oct 2025 - Sep 2026 (analysis.py)
A14: Department | B14: Fixed cost / month ($) | C14: Variable rate (% of revenue)
A15: Store Operations | B15: 9667912 | C15: 0.05203584
A16: Marketing | B16: 1062931.4 | C16: 0.03519224
A17: Supply Chain & Logistics | B17: 1899521.4 | C17: 0.03279161
A18: Technology | B18: 1718203.2 | C18: 0.00718841
A19: General & Administrative | B19: 4441154.5 | C19: 0.00031673
A21: Fixed and variable splits are OLS fits of monthly department cost on revenue, trailing 12 months (analysis.py).

Sheet Data
A1: Month | B1: Scenario | C1: Line item | D1: Amount ($) | F1: Forecast month | G1: Base revenue forecast ($)
A2: 2026-01 | B2: Budget | C2: Cost of Goods Sold | D2: -54337297 | F2: 2026-10 | G2: 112395510
A3: 2026-01 | B3: Actual | C3: Cost of Goods Sold | D3: -54879491 | F3: 2026-11 | G3: 149730186
A4: 2026-01 | B4: Budget | C4: General & Administrative | D4: -4395523 | F4: 2026-12 | G4: 173779417
A5: 2026-01 | B5: Actual | C5: General & Administrative | D5: -4543145 | F5: 2027-01 | G5: 92922171
A6: 2026-01 | B6: Budget | C6: Marketing | D6: -4166309 | F6: 2027-02 | G6: 86581544
A7: 2026-01 | B7: Actual | C7: Marketing | D7: -4142386 | F7: 2027-03 | G7: 104542391
A8: 2026-01 | B8: Budget | C8: Revenue | D8: 87640800 | F8: 2027-04 | G8: 114961469
A9: 2026-01 | B9: Actual | C9: Revenue | D9: 87881939 | F9: 2027-05 | G9: 126619163
A10: 2026-01 | B10: Budget | C10: Store Operations | D10: -14346125 | F10: 2027-06 | G10: 134037068
A11: 2026-01 | B11: Actual | C11: Store Operations | D11: -14406840 | F11: 2027-07 | G11: 131622563
A12: 2026-01 | B12: Budget | C12: Supply Chain & Logistics | D12: -4752828 | F12: 2027-08 | G12: 122513825
A13: 2026-01 | B13: Actual | C13: Supply Chain & Logistics | D13: -4937228 | F13: 2027-09 | G13: 114465127
A14: 2026-01 | B14: Budget | C14: Technology | D14: -2716303
A15: 2026-01 | B15: Actual | C15: Technology | D15: -2382813 | F15: Source: analysis.py model output (sum of region x channel models)
A16: 2026-02 | B16: Budget | C16: Cost of Goods Sold | D16: -50157504
A17: 2026-02 | B17: Actual | C17: Cost of Goods Sold | D17: -50845745
A18: 2026-02 | B18: Budget | C18: General & Administrative | D18: -4368557
A19: 2026-02 | B19: Actual | C19: General & Administrative | D19: -4386297
A20: 2026-02 | B20: Budget | C20: Marketing | D20: -3923611
A21: 2026-02 | B21: Actual | C21: Marketing | D21: -3990024
A22: 2026-02 | B22: Budget | C22: Revenue | D22: 80899200
A23: 2026-02 | B23: Actual | C23: Revenue | D23: 81457342
A24: 2026-02 | B24: Budget | C24: Store Operations | D24: -13968595
A25: 2026-02 | B25: Actual | C25: Store Operations | D25: -13690807
A26: 2026-02 | B26: Budget | C26: Supply Chain & Logistics | D26: -4516872
A27: 2026-02 | B27: Actual | C27: Supply Chain & Logistics | D27: -4565386
... A148: 2026-12 | B148: Budget | C148: Technology | D148: -2994394

Sheet Budget vs Actual
A1: FY2026 Budget vs. Actual ($000s)
A2: Actuals through Sep 2026. Variance = Actual - Budget; positive is favorable.
A4: Line item | B4: Type | C4: 2026-01 | D4: 2026-02 | E4: 2026-03 | F4: 2026-04 | G4: 2026-05 | H4: 2026-06 | I4: 2026-07 | J4: 2026-08 | K4: 2026-09 | L4: 2026-10 | M4: 2026-11 | N4: 2026-12 | O4: YTD Budget | P4: YTD Actual | Q4: YTD Var $ | R4: YTD Var % | S4: FY Budget | T4: FY Latest Est. | U4: FY Var $
A5: Revenue | B5: Budget | C5: =SUMIFS(Data!$D$2:$D$148,Data!$A$2:$A$148,"2026-01",Data!$B$2:$B$148,"Budget",Data!$C$2:$C$148,"Revenue") -> 87640800 | D5: =SUMIFS(Data!$D$2:$D$148,Data!$A$2:$A$148,"2026-02",Data!$B$2:$B$148,"Budget",Data!$C$2:$C$148,"Revenue") -> 80899200 | E5: =SUMIFS(Data!$D$2:$D$148,Data!$A$2:$A$148,"2026-03",Data!$B$2:$B$148,"Budget",Data!$C$2:$C$148,"Revenue") -> 97079040 | F5: =SUMIFS(Data!$D$2:$D$148,Data!$A$2:$A$148,"2026-04",Data!$B$2:$B$148,"Budget",Data!$C$2:$C$148,"Revenue") -> 105168959 | G5: =SUMIFS(Data!$D$2:$D$148,Data!$A$2:$A$148,"2026-05",Data!$B$2:$B$148,"Budget",Data!$C$2:$C$148,"Revenue") -> 114607200 | H5: =SUMIFS(Data!$D$2:$D$148,Data!$A$2:$A$148,"2026-06",Data!$B$2:$B$148,"Budget",Data!$C$2:$C$148,"Revenue") -> 121348800 | I5: =SUMIFS(Data!$D$2:$D$148,Data!$A$2:$A$148,"2026-07",Data!$B$2:$B$148,"Budget",Data!$C$2:$C$148,"Revenue") -> 118652160 | J5: =SUMIFS(Data!$D$2:$D$148,Data!$A$2:$A$148,"2026-08",Data!$B$2:$B$148,"Budget",Data!$C$2:$C$148,"Revenue") -> 110562240 | K5: =SUMIFS(Data!$D$2:$D$148,Data!$A$2:$A$148,"2026-09",Data!$B$2:$B$148,"Budget",Data!$C$2:$C$148,"Revenue") -> 101124000 | L5: =SUMIFS(Data!$D$2:$D$148,Data!$A$2:$A$148,"2026-10",Data!$B$2:$B$148,"Budget",Data!$C$2:$C$148,"Revenue") -> 107865600 | M5: =SUMIFS(Data!$D$2:$D$148,Data!$A$2:$A$148,"2026-11",Data!$B$2:$B$148,"Budget",Data!$C$2:$C$148,"Revenue") -> 141573600 | N5: =SUMIFS(Data!$D$2:$D$148,Data!$A$2:$A$148,"2026-12",Data!$B$2:$B$148,"Budget",Data!$C$2:$C$148,"Revenue") -> 161798400 | O5: =SUM(C5:K5) -> 937082399 | P5: =SUM(C6:K6) -> 966815477 | Q5: =P5-O5 -> 29733078 | R5: =IF(O5=0,0,Q5/ABS(O5)) -> 0.031729417 | S5: =SUM(C5:N5) -> 1348319999 | T5: =P5+SUM(Forecast!B5:D5) -> 1402720590 | U5: =T5-S5 -> 54400591
B6: Actual | C6: =SUMIFS(Data!$D$2:$D$148,Data!$A$2:$A$148,"2026-01",Data!$B$2:$B$148,"Actual",Data!$C$2:$C$148,"Revenue") -> 87881939 | D6: =SUMIFS(Data!$D$2:$D$148,Data!$A$2:$A$148,"2026-02",Data!$B$2:$B$148,"Actual",Data!$C$2:$C$148,"Revenue") -> 81457342 | E6: =SUMIFS(Data!$D$2:$D$148,Data!$A$2:$A$148,"2026-03",Data!$B$2:$B$148,"Actual",Data!$C$2:$C$148,"Revenue") -> 98901801 | F6: =SUMIFS(Data!$D$2:$D$148,Data!$A$2:$A$148,"2026-04",Data!$B$2:$B$148,"Actual",Data!$C$2:$C$148,"Revenue") -> 107856468 | G6: =SUMIFS(Data!$D$2:$D$148,Data!$A$2:$A$148,"2026-05",Data!$B$2:$B$148,"Actual",Data!$C$2:$C$148,"Revenue") -> 120266325 | H6: =SUMIFS(Data!$D$2:$D$148,Data!$A$2:$A$148,"2026-06",Data!$B$2:$B$148,"Actual",Data!$C$2:$C$148,"Revenue") -> 126029689 | I6: =SUMIFS(Data!$D$2:$D$148,Data!$A$2:$A$148,"2026-07",Data!$B$2:$B$148,"Actual",Data!$C$2:$C$148,"Revenue") -> 123314199 | J6: =SUMIFS(Data!$D$2:$D$148,Data!$A$2:$A$148,"2026-08",Data!$B$2:$B$148,"Actual",Data!$C$2:$C$148,"Revenue") -> 113220467 | K6: =SUMIFS(Data!$D$2:$D$148,Data!$A$2:$A$148,"2026-09",Data!$B$2:$B$148,"Actual",Data!$C$2:$C$148,"Revenue") -> 107887247
B7: Variance $ | C7: =IF(C6="","",C6-C5) -> 241139 | D7: =IF(D6="","",D6-D5) -> 558142 | E7: =IF(E6="","",E6-E5) -> 1822761 | F7: =IF(F6="","",F6-F5) -> 2687509 | G7: =IF(G6="","",G6-G5) -> 5659125 | H7: =IF(H6="","",H6-H5) -> 4680889 | I7: =IF(I6="","",I6-I5) -> 4662039 | J7: =IF(J6="","",J6-J5) -> 2658227 | ... N7: =IF(N6="","",N6-N5)
A8: Cost of Goods Sold | B8: Budget | C8: =SUMIFS(Data!$D$2:$D$148,Data!$A$2:$A$148,"2026-01",Data!$B$2:$B$148,"Budget",Data!$C$2:$C$148,"Cost of Goods Sold") -> -54337297 | D8: =SUMIFS(Data!$D$2:$D$148,Data!$A$2:$A$148,"2026-02",Data!$B$2:$B$148,"Budget",Data!$C$2:$C$148,"Cost of Goods Sold") -> -50157504 | E8: =SUMIFS(Data!$D$2:$D$148,Data!$A$2:$A$148,"2026-03",Data!$B$2:$B$148,"Budget",Data!$C$2:$C$148,"Cost of Goods Sold") -> -60189004 | F8: =SUMIFS(Data!$D$2:$D$148,Data!$A$2:$A$148,"2026-04",Data!$B$2:$B$148,"Budget",Data!$C$2:$C$148,"Cost of Goods Sold") -> -65204756 | G8: =SUMIFS(Data!$D$2:$D$148,Data!$A$2:$A$148,"2026-05",Data!$B$2:$B$148,"Budget",Data!$C$2:$C$148,"Cost of Goods Sold") -> -71056463 | H8: =SUMIFS(Data!$D$2:$D$148,Data!$A$2:$A$148,"2026-06",Data!$B$2:$B$148,"Budget",Data!$C$2:$C$148,"Cost of Goods Sold") -> -75236255 | I8: =SUMIFS(Data!$D$2:$D$148,Data!$A$2:$A$148,"2026-07",Data!$B$2:$B$148,"Budget",Data!$C$2:$C$148,"Cost of Goods Sold") -> -73564339 | J8: =SUMIFS(Data!$D$2:$D$148,Data!$A$2:$A$148,"2026-08",Data!$B$2:$B$148,"Budget",Data!$C$2:$C$148,"Cost of Goods Sold") -> -68548589 | K8: =SUMIFS(Data!$D$2:$D$148,Data!$A$2:$A$148,"2026-09",Data!$B$2:$B$148,"Budget",Data!$C$2:$C$148,"Cost of Goods Sold") -> -62696880 | L8: =SUMIFS(Data!$D$2:$D$148,Data!$A$2:$A$148,"2026-10",Data!$B$2:$B$148,"Budget",Data!$C$2:$C$148,"Cost of Goods Sold") -> -66876672 | M8: =SUMIFS(Data!$D$2:$D$148,Data!$A$2:$A$148,"2026-11",Data!$B$2:$B$148,"Budget",Data!$C$2:$C$148,"Cost of Goods Sold") -> -87775631 | N8: =SUMIFS(Data!$D$2:$D$148,Data!$A$2:$A$148,"2026-12",Data!$B$2:$B$148,"Budget",Data!$C$2:$C$148,"Cost of Goods Sold") -> -100315007 | O8: =SUM(C8:K8) -> -580991087 | P8: =SUM(C9:K9) -> -602830011 | Q8: =P8-O8 -> -21838924 | R8: =IF(O8=0,0,Q8/ABS(O8)) -> -0.037589086 | S8: =SUM(C8:N8) -> -835958397 | T8: =P8+SUM(Forecast!B6:D6) -> -8.7441266e+08 | U8: =T8-S8 -> -38454265
B9: Actual | C9: =SUMIFS(Data!$D$2:$D$148,Data!$A$2:$A$148,"2026-01",Data!$B$2:$B$148,"Actual",Data!$C$2:$C$148,"Cost of Goods Sold") -> -54879491 | D9: =SUMIFS(Data!$D$2:$D$148,Data!$A$2:$A$148,"2026-02",Data!$B$2:$B$148,"Actual",Data!$C$2:$C$148,"Cost of Goods Sold") -> -50845745 | E9: =SUMIFS(Data!$D$2:$D$148,Data!$A$2:$A$148,"2026-03",Data!$B$2:$B$148,"Actual",Data!$C$2:$C$148,"Cost of Goods Sold") -> -61506987 | F9: =SUMIFS(Data!$D$2:$D$148,Data!$A$2:$A$148,"2026-04",Data!$B$2:$B$148,"Actual",Data!$C$2:$C$148,"Cost of Goods Sold") -> -67532577 | G9: =SUMIFS(Data!$D$2:$D$148,Data!$A$2:$A$148,"2026-05",Data!$B$2:$B$148,"Actual",Data!$C$2:$C$148,"Cost of Goods Sold") -> -74895410 | H9: =SUMIFS(Data!$D$2:$D$148,Data!$A$2:$A$148,"2026-06",Data!$B$2:$B$148,"Actual",Data!$C$2:$C$148,"Cost of Goods Sold") -> -78590907 | I9: =SUMIFS(Data!$D$2:$D$148,Data!$A$2:$A$148,"2026-07",Data!$B$2:$B$148,"Actual",Data!$C$2:$C$148,"Cost of Goods Sold") -> -76562659 | J9: =SUMIFS(Data!$D$2:$D$148,Data!$A$2:$A$148,"2026-08",Data!$B$2:$B$148,"Actual",Data!$C$2:$C$148,"Cost of Goods Sold") -> -70688494 | K9: =SUMIFS(Data!$D$2:$D$148,Data!$A$2:$A$148,"2026-09",Data!$B$2:$B$148,"Actual",Data!$C$2:$C$148,"Cost of Goods Sold") -> -67327741
B10: Variance $ | C10: =IF(C9="","",C9-C8) -> -542194 | D10: =IF(D9="","",D9-D8) -> -688241 | E10: =IF(E9="","",E9-E8) -> -1317983 | F10: =IF(F9="","",F9-F8) -> -2327821 | G10: =IF(G9="","",G9-G8) -> -3838947 | H10: =IF(H9="","",H9-H8) -> -3354652 | I10: =IF(I9="","",I9-I8) -> -2998320 | J10: =IF(J9="","",J9-J8) -> -2139905 | ... N10: =IF(N9="","",N9-N8)
A11: Gross Profit | B11: Budget | C11: =C5+C8 -> 33303503 | D11: =D5+D8 -> 30741696 | E11: =E5+E8 -> 36890036 | F11: =F5+F8 -> 39964203 | G11: =G5+G8 -> 43550737 | H11: =H5+H8 -> 46112545 | I11: =I5+I8 -> 45087821 | J11: =J5+J8 -> 42013651 | ... N11: =N5+N8 -> 61483393 | O11: =SUM(C11:K11) -> 356091312 | P11: =SUM(C12:K12) -> 363985466 | Q11: =P11-O11 -> 7894154 | R11: =IF(O11=0,0,Q11/ABS(O11)) -> 0.022168904 | S11: =SUM(C11:N11) -> 512361602 | T11: =P11+SUM(Forecast!B7:D7) -> 5.2830793e+08 | U11: =T11-S11 -> 15946326
B12: Actual | C12: =C6+C9 -> 33002448 | D12: =D6+D9 -> 30611597 | E12: =E6+E9 -> 37394814 | F12: =F6+F9 -> 40323891 | G12: =G6+G9 -> 45370915 | H12: =H6+H9 -> 47438782 | I12: =I6+I9 -> 46751540 | J12: =J6+J9 -> 42531973 | K12: =K6+K9 -> 40559506
B13: Variance $ | C13: =IF(C12="","",C12-C11) -> -301055 | D13: =IF(D12="","",D12-D11) -> -130099 | E13: =IF(E12="","",E12-E11) -> 504778 | F13: =IF(F12="","",F12-F11) -> 359688 | G13: =IF(G12="","",G12-G11) -> 1820178 | H13: =IF(H12="","",H12-H11) -> 1326237 | I13: =IF(I12="","",I12-I11) -> 1663719 | J13: =IF(J12="","",J12-J11) -> 518322 | ... N13: =IF(N12="","",N12-N11)
A14: Store Operations | B14: Budget | C14: =SUMIFS(Data!$D$2:$D$148,Data!$A$2:$A$148,"2026-01",Data!$B$2:$B$148,"Budget",Data!$C$2:$C$148,"Store Operations") -> -14346125 | D14: =SUMIFS(Data!$D$2:$D$148,Data!$A$2:$A$148,"2026-02",Data!$B$2:$B$148,"Budget",Data!$C$2:$C$148,"Store Operations") -> -13968595 | E14: =SUMIFS(Data!$D$2:$D$148,Data!$A$2:$A$148,"2026-03",Data!$B$2:$B$148,"Budget",Data!$C$2:$C$148,"Store Operations") -> -14874666 | F14: =SUMIFS(Data!$D$2:$D$148,Data!$A$2:$A$148,"2026-04",Data!$B$2:$B$148,"Budget",Data!$C$2:$C$148,"Store Operations") -> -15327702 | G14: =SUMIFS(Data!$D$2:$D$148,Data!$A$2:$A$148,"2026-05",Data!$B$2:$B$148,"Budget",Data!$C$2:$C$148,"Store Operations") -> -15856243 | H14: =SUMIFS(Data!$D$2:$D$148,Data!$A$2:$A$148,"2026-06",Data!$B$2:$B$148,"Budget",Data!$C$2:$C$148,"Store Operations") -> -16233773 | I14: =SUMIFS(Data!$D$2:$D$148,Data!$A$2:$A$148,"2026-07",Data!$B$2:$B$148,"Budget",Data!$C$2:$C$148,"Store Operations") -> -16082761 | J14: =SUMIFS(Data!$D$2:$D$148,Data!$A$2:$A$148,"2026-08",Data!$B$2:$B$148,"Budget",Data!$C$2:$C$148,"Store Operations") -> -15629725 | K14: =SUMIFS(Data!$D$2:$D$148,Data!$A$2:$A$148,"2026-09",Data!$B$2:$B$148,"Budget",Data!$C$2:$C$148,"Store Operations") -> -15101184 | L14: =SUMIFS(Data!$D$2:$D$148,Data!$A$2:$A$148,"2026-10",Data!$B$2:$B$148,"Budget",Data!$C$2:$C$148,"Store Operations") -> -15478714 | M14: =SUMIFS(Data!$D$2:$D$148,Data!$A$2:$A$148,"2026-11",Data!$B$2:$B$148,"Budget",Data!$C$2:$C$148,"Store Operations") -> -17366362 | N14: =SUMIFS(Data!$D$2:$D$148,Data!$A$2:$A$148,"2026-12",Data!$B$2:$B$148,"Budget",Data!$C$2:$C$148,"Store Operations") -> -18498950 | O14: =SUM(C14:K14) -> -137420774 | P14: =SUM(C15:K15) -> -138297842 | Q14: =P14-O14 -> -877068 | R14: =IF(O14=0,0,Q14/ABS(O14)) -> -0.0063823538 | S14: =SUM(C14:N14) -> -188764800 | T14: =P14+SUM(Forecast!B8:D8) -> -1.8998427e+08 | U14: =T14-S14 -> -1219466.6
B15: Actual | C15: =SUMIFS(Data!$D$2:$D$148,Data!$A$2:$A$148,"2026-01",Data!$B$2:$B$148,"Actual",Data!$C$2:$C$148,"Store Operations") -> -14406840 | D15: =SUMIFS(Data!$D$2:$D$148,Data!$A$2:$A$148,"2026-02",Data!$B$2:$B$148,"Actual",Data!$C$2:$C$148,"Store Operations") -> -13690807 | E15: =SUMIFS(Data!$D$2:$D$148,Data!$A$2:$A$148,"2026-03",Data!$B$2:$B$148,"Actual",Data!$C$2:$C$148,"Store Operations") -> -15339932 | F15: =SUMIFS(Data!$D$2:$D$148,Data!$A$2:$A$148,"2026-04",Data!$B$2:$B$148,"Actual",Data!$C$2:$C$148,"Store Operations") -> -15372226 | G15: =SUMIFS(Data!$D$2:$D$148,Data!$A$2:$A$148,"2026-05",Data!$B$2:$B$148,"Actual",Data!$C$2:$C$148,"Store Operations") -> -16004074 | H15: =SUMIFS(Data!$D$2:$D$148,Data!$A$2:$A$148,"2026-06",Data!$B$2:$B$148,"Actual",Data!$C$2:$C$148,"Store Operations") -> -16061457 | I15: =SUMIFS(Data!$D$2:$D$148,Data!$A$2:$A$148,"2026-07",Data!$B$2:$B$148,"Actual",Data!$C$2:$C$148,"Store Operations") -> -16470566 | J15: =SUMIFS(Data!$D$2:$D$148,Data!$A$2:$A$148,"2026-08",Data!$B$2:$B$148,"Actual",Data!$C$2:$C$148,"Store Operations") -> -15614071 | K15: =SUMIFS(Data!$D$2:$D$148,Data!$A$2:$A$148,"2026-09",Data!$B$2:$B$148,"Actual",Data!$C$2:$C$148,"Store Operations") -> -15337869
B16: Variance $ | C16: =IF(C15="","",C15-C14) -> -60715 | D16: =IF(D15="","",D15-D14) -> 277788 | E16: =IF(E15="","",E15-E14) -> -465266 | F16: =IF(F15="","",F15-F14) -> -44524 | G16: =IF(G15="","",G15-G14) -> -147831 | H16: =IF(H15="","",H15-H14) -> 172316 | I16: =IF(I15="","",I15-I14) -> -387805 | J16: =IF(J15="","",J15-J14) -> 15654 | ... N16: =IF(N15="","",N15-N14)
A17: Marketing | B17: Budget | C17: =SUMIFS(Data!$D$2:$D$148,Data!$A$2:$A$148,"2026-01",Data!$B$2:$B$148,"Budget",Data!$C$2:$C$148,"Marketing") -> -4166309 | D17: =SUMIFS(Data!$D$2:$D$148,Data!$A$2:$A$148,"2026-02",Data!$B$2:$B$148,"Budget",Data!$C$2:$C$148,"Marketing") -> -3923611 | E17: =SUMIFS(Data!$D$2:$D$148,Data!$A$2:$A$148,"2026-03",Data!$B$2:$B$148,"Budget",Data!$C$2:$C$148,"Marketing") -> -4506085 | F17: =SUMIFS(Data!$D$2:$D$148,Data!$A$2:$A$148,"2026-04",Data!$B$2:$B$148,"Budget",Data!$C$2:$C$148,"Marketing") -> -4797323 | G17: =SUMIFS(Data!$D$2:$D$148,Data!$A$2:$A$148,"2026-05",Data!$B$2:$B$148,"Budget",Data!$C$2:$C$148,"Marketing") -> -5137099 | H17: =SUMIFS(Data!$D$2:$D$148,Data!$A$2:$A$148,"2026-06",Data!$B$2:$B$148,"Budget",Data!$C$2:$C$148,"Marketing") -> -5379797 | I17: =SUMIFS(Data!$D$2:$D$148,Data!$A$2:$A$148,"2026-07",Data!$B$2:$B$148,"Budget",Data!$C$2:$C$148,"Marketing") -> -5282718 | J17: =SUMIFS(Data!$D$2:$D$148,Data!$A$2:$A$148,"2026-08",Data!$B$2:$B$148,"Budget",Data!$C$2:$C$148,"Marketing") -> -4991481 | K17: =SUMIFS(Data!$D$2:$D$148,Data!$A$2:$A$148,"2026-09",Data!$B$2:$B$148,"Budget",Data!$C$2:$C$148,"Marketing") -> -4651704 | L17: =SUMIFS(Data!$D$2:$D$148,Data!$A$2:$A$148,"2026-10",Data!$B$2:$B$148,"Budget",Data!$C$2:$C$148,"Marketing") -> -4894402 | M17: =SUMIFS(Data!$D$2:$D$148,Data!$A$2:$A$148,"2026-11",Data!$B$2:$B$148,"Budget",Data!$C$2:$C$148,"Marketing") -> -6107890 | N17: =SUMIFS(Data!$D$2:$D$148,Data!$A$2:$A$148,"2026-12",Data!$B$2:$B$148,"Budget",Data!$C$2:$C$148,"Marketing") -> -6835982 | O17: =SUM(C17:K17) -> -42836127 | P17: =SUM(C18:K18) -> -43597347 | Q17: =P17-O17 -> -761220 | R17: =IF(O17=0,0,Q17/ABS(O17)) -> -0.017770514 | S17: =SUM(C17:N17) -> -60674401 | T17: =P17+SUM(Forecast!B9:D9) -> -62126619 | U17: =T17-S17 -> -1452217.7
B18: Actual | C18: =SUMIFS(Data!$D$2:$D$148,Data!$A$2:$A$148,"2026-01",Data!$B$2:$B$148,"Actual",Data!$C$2:$C$148,"Marketing") -> -4142386 | D18: =SUMIFS(Data!$D$2:$D$148,Data!$A$2:$A$148,"2026-02",Data!$B$2:$B$148,"Actual",Data!$C$2:$C$148,"Marketing") -> -3990024 | E18: =SUMIFS(Data!$D$2:$D$148,Data!$A$2:$A$148,"2026-03",Data!$B$2:$B$148,"Actual",Data!$C$2:$C$148,"Marketing") -> -4542099 | F18: =SUMIFS(Data!$D$2:$D$148,Data!$A$2:$A$148,"2026-04",Data!$B$2:$B$148,"Actual",Data!$C$2:$C$148,"Marketing") -> -4886087 | G18: =SUMIFS(Data!$D$2:$D$148,Data!$A$2:$A$148,"2026-05",Data!$B$2:$B$148,"Actual",Data!$C$2:$C$148,"Marketing") -> -5066871 | H18: =SUMIFS(Data!$D$2:$D$148,Data!$A$2:$A$148,"2026-06",Data!$B$2:$B$148,"Actual",Data!$C$2:$C$148,"Marketing") -> -5641055 | I18: =SUMIFS(Data!$D$2:$D$148,Data!$A$2:$A$148,"2026-07",Data!$B$2:$B$148,"Actual",Data!$C$2:$C$148,"Marketing") -> -5432354 | J18: =SUMIFS(Data!$D$2:$D$148,Data!$A$2:$A$148,"2026-08",Data!$B$2:$B$148,"Actual",Data!$C$2:$C$148,"Marketing") -> -5042877 | K18: =SUMIFS(Data!$D$2:$D$148,Data!$A$2:$A$148,"2026-09",Data!$B$2:$B$148,"Actual",Data!$C$2:$C$148,"Marketing") -> -4853594
B19: Variance $ | C19: =IF(C18="","",C18-C17) -> 23923 | D19: =IF(D18="","",D18-D17) -> -66413 | E19: =IF(E18="","",E18-E17) -> -36014 | F19: =IF(F18="","",F18-F17) -> -88764 | G19: =IF(G18="","",G18-G17) -> 70228 | H19: =IF(H18="","",H18-H17) -> -261258 | I19: =IF(I18="","",I18-I17) -> -149636 | J19: =IF(J18="","",J18-J17) -> -51396 | ... N19: =IF(N18="","",N18-N17)
A20: Supply Chain & Logistics | B20: Budget | C20: =SUMIFS(Data!$D$2:$D$148,Data!$A$2:$A$148,"2026-01",Data!$B$2:$B$148,"Budget",Data!$C$2:$C$148,"Supply Chain & Logistics") -> -4752828 | D20: =SUMIFS(Data!$D$2:$D$148,Data!$A$2:$A$148,"2026-02",Data!$B$2:$B$148,"Budget",Data!$C$2:$C$148,"Supply Chain & Logistics") -> -4516872 | E20: =SUMIFS(Data!$D$2:$D$148,Data!$A$2:$A$148,"2026-03",Data!$B$2:$B$148,"Budget",Data!$C$2:$C$148,"Supply Chain & Logistics") -> -5083166 | F20: =SUMIFS(Data!$D$2:$D$148,Data!$A$2:$A$148,"2026-04",Data!$B$2:$B$148,"Budget",Data!$C$2:$C$148,"Supply Chain & Logistics") -> -5366314 | G20: =SUMIFS(Data!$D$2:$D$148,Data!$A$2:$A$148,"2026-05",Data!$B$2:$B$148,"Budget",Data!$C$2:$C$148,"Supply Chain & Logistics") -> -5696652 | H20: =SUMIFS(Data!$D$2:$D$148,Data!$A$2:$A$148,"2026-06",Data!$B$2:$B$148,"Budget",Data!$C$2:$C$148,"Supply Chain & Logistics") -> -5932608 | I20: =SUMIFS(Data!$D$2:$D$148,Data!$A$2:$A$148,"2026-07",Data!$B$2:$B$148,"Budget",Data!$C$2:$C$148,"Supply Chain & Logistics") -> -5838226 | J20: =SUMIFS(Data!$D$2:$D$148,Data!$A$2:$A$148,"2026-08",Data!$B$2:$B$148,"Budget",Data!$C$2:$C$148,"Supply Chain & Logistics") -> -5555078 | K20: =SUMIFS(Data!$D$2:$D$148,Data!$A$2:$A$148,"2026-09",Data!$B$2:$B$148,"Budget",Data!$C$2:$C$148,"Supply Chain & Logistics") -> -5224740 | L20: =SUMIFS(Data!$D$2:$D$148,Data!$A$2:$A$148,"2026-10",Data!$B$2:$B$148,"Budget",Data!$C$2:$C$148,"Supply Chain & Logistics") -> -5460696 | M20: =SUMIFS(Data!$D$2:$D$148,Data!$A$2:$A$148,"2026-11",Data!$B$2:$B$148,"Budget",Data!$C$2:$C$148,"Supply Chain & Logistics") -> -6640476 | N20: =SUMIFS(Data!$D$2:$D$148,Data!$A$2:$A$148,"2026-12",Data!$B$2:$B$148,"Budget",Data!$C$2:$C$148,"Supply Chain & Logistics") -> -7348344 | O20: =SUM(C20:K20) -> -47966484 | P20: =SUM(C21:K21) -> -49064988 | Q20: =P20-O20 -> -1098504 | R20: =IF(O20=0,0,Q20/ABS(O20)) -> -0.022901491 | S20: =SUM(C20:N20) -> -67416000 | T20: =P20+SUM(Forecast!B10:D10) -> -69057583 | U20: =T20-S20 -> -1641582.7
B21: Actual | C21: =SUMIFS(Data!$D$2:$D$148,Data!$A$2:$A$148,"2026-01",Data!$B$2:$B$148,"Actual",Data!$C$2:$C$148,"Supply Chain & Logistics") -> -4937228 | D21: =SUMIFS(Data!$D$2:$D$148,Data!$A$2:$A$148,"2026-02",Data!$B$2:$B$148,"Actual",Data!$C$2:$C$148,"Supply Chain & Logistics") -> -4565386 | E21: =SUMIFS(Data!$D$2:$D$148,Data!$A$2:$A$148,"2026-03",Data!$B$2:$B$148,"Actual",Data!$C$2:$C$148,"Supply Chain & Logistics") -> -4972794 | F21: =SUMIFS(Data!$D$2:$D$148,Data!$A$2:$A$148,"2026-04",Data!$B$2:$B$148,"Actual",Data!$C$2:$C$148,"Supply Chain & Logistics") -> -5274106 | G21: =SUMIFS(Data!$D$2:$D$148,Data!$A$2:$A$148,"2026-05",Data!$B$2:$B$148,"Actual",Data!$C$2:$C$148,"Supply Chain & Logistics") -> -5987250 | H21: =SUMIFS(Data!$D$2:$D$148,Data!$A$2:$A$148,"2026-06",Data!$B$2:$B$148,"Actual",Data!$C$2:$C$148,"Supply Chain & Logistics") -> -6139035 | I21: =SUMIFS(Data!$D$2:$D$148,Data!$A$2:$A$148,"2026-07",Data!$B$2:$B$148,"Actual",Data!$C$2:$C$148,"Supply Chain & Logistics") -> -6099433 | J21: =SUMIFS(Data!$D$2:$D$148,Data!$A$2:$A$148,"2026-08",Data!$B$2:$B$148,"Actual",Data!$C$2:$C$148,"Supply Chain & Logistics") -> -5593996 | K21: =SUMIFS(Data!$D$2:$D$148,Data!$A$2:$A$148,"2026-09",Data!$B$2:$B$148,"Actual",Data!$C$2:$C$148,"Supply Chain & Logistics") -> -5495760
B22: Variance $ | C22: =IF(C21="","",C21-C20) -> -184400 | D22: =IF(D21="","",D21-D20) -> -48514 | E22: =IF(E21="","",E21-E20) -> 110372 | F22: =IF(F21="","",F21-F20) -> 92208 | G22: =IF(G21="","",G21-G20) -> -290598 | H22: =IF(H21="","",H21-H20) -> -206427 | I22: =IF(I21="","",I21-I20) -> -261207 | J22: =IF(J21="","",J21-J20) -> -38918 | ... N22: =IF(N21="","",N21-N20)
A23: Technology | B23: Budget | C23: =SUMIFS(Data!$D$2:$D$148,Data!$A$2:$A$148,"2026-01",Data!$B$2:$B$148,"Budget",Data!$C$2:$C$148,"Technology") -> -2716303 | D23: =SUMIFS(Data!$D$2:$D$148,Data!$A$2:$A$148,"2026-02",Data!$B$2:$B$148,"Budget",Data!$C$2:$C$148,"Technology") -> -2691022 | E23: =SUMIFS(Data!$D$2:$D$148,Data!$A$2:$A$148,"2026-03",Data!$B$2:$B$148,"Budget",Data!$C$2:$C$148,"Technology") -> -2751696 | F23: =SUMIFS(Data!$D$2:$D$148,Data!$A$2:$A$148,"2026-04",Data!$B$2:$B$148,"Budget",Data!$C$2:$C$148,"Technology") -> -2782034 | G23: =SUMIFS(Data!$D$2:$D$148,Data!$A$2:$A$148,"2026-05",Data!$B$2:$B$148,"Budget",Data!$C$2:$C$148,"Technology") -> -2817427 | H23: =SUMIFS(Data!$D$2:$D$148,Data!$A$2:$A$148,"2026-06",Data!$B$2:$B$148,"Budget",Data!$C$2:$C$148,"Technology") -> -2842708 | I23: =SUMIFS(Data!$D$2:$D$148,Data!$A$2:$A$148,"2026-07",Data!$B$2:$B$148,"Budget",Data!$C$2:$C$148,"Technology") -> -2832596 | J23: =SUMIFS(Data!$D$2:$D$148,Data!$A$2:$A$148,"2026-08",Data!$B$2:$B$148,"Budget",Data!$C$2:$C$148,"Technology") -> -2802258 | K23: =SUMIFS(Data!$D$2:$D$148,Data!$A$2:$A$148,"2026-09",Data!$B$2:$B$148,"Budget",Data!$C$2:$C$148,"Technology") -> -2766865 | L23: =SUMIFS(Data!$D$2:$D$148,Data!$A$2:$A$148,"2026-10",Data!$B$2:$B$148,"Budget",Data!$C$2:$C$148,"Technology") -> -2792146 | M23: =SUMIFS(Data!$D$2:$D$148,Data!$A$2:$A$148,"2026-11",Data!$B$2:$B$148,"Budget",Data!$C$2:$C$148,"Technology") -> -2918551 | N23: =SUMIFS(Data!$D$2:$D$148,Data!$A$2:$A$148,"2026-12",Data!$B$2:$B$148,"Budget",Data!$C$2:$C$148,"Technology") -> -2994394 | O23: =SUM(C23:K23) -> -25002909 | P23: =SUM(C24:K24) -> -22162877 | Q23: =P23-O23 -> 2840032 | R23: =IF(O23=0,0,Q23/ABS(O23)) -> 0.11358806 | S23: =SUM(C23:N23) -> -33708000 | T23: =P23+SUM(Forecast!B11:D11) -> -30450951 | U23: =T23-S23 -> 3257048.8
B24: Actual | C24: =SUMIFS(Data!$D$2:$D$148,Data!$A$2:$A$148,"2026-01",Data!$B$2:$B$148,"Actual",Data!$C$2:$C$148,"Technology") -> -2382813 | D24: =SUMIFS(Data!$D$2:$D$148,Data!$A$2:$A$148,"2026-02",Data!$B$2:$B$148,"Actual",Data!$C$2:$C$148,"Technology") -> -2328749 | E24: =SUMIFS(Data!$D$2:$D$148,Data!$A$2:$A$148,"2026-03",Data!$B$2:$B$148,"Actual",Data!$C$2:$C$148,"Technology") -> -2426655 | F24: =SUMIFS(Data!$D$2:$D$148,Data!$A$2:$A$148,"2026-04",Data!$B$2:$B$148,"Actual",Data!$C$2:$C$148,"Technology") -> -2377663 | G24: =SUMIFS(Data!$D$2:$D$148,Data!$A$2:$A$148,"2026-05",Data!$B$2:$B$148,"Actual",Data!$C$2:$C$148,"Technology") -> -2511619 | H24: =SUMIFS(Data!$D$2:$D$148,Data!$A$2:$A$148,"2026-06",Data!$B$2:$B$148,"Actual",Data!$C$2:$C$148,"Technology") -> -2636972 | I24: =SUMIFS(Data!$D$2:$D$148,Data!$A$2:$A$148,"2026-07",Data!$B$2:$B$148,"Actual",Data!$C$2:$C$148,"Technology") -> -2539424 | J24: =SUMIFS(Data!$D$2:$D$148,Data!$A$2:$A$148,"2026-08",Data!$B$2:$B$148,"Actual",Data!$C$2:$C$148,"Technology") -> -2513900 | K24: =SUMIFS(Data!$D$2:$D$148,Data!$A$2:$A$148,"2026-09",Data!$B$2:$B$148,"Actual",Data!$C$2:$C$148,"Technology") -> -2445082
B25: Variance $ | C25: =IF(C24="","",C24-C23) -> 333490 | D25: =IF(D24="","",D24-D23) -> 362273 | E25: =IF(E24="","",E24-E23) -> 325041 | F25: =IF(F24="","",F24-F23) -> 404371 | G25: =IF(G24="","",G24-G23) -> 305808 | H25: =IF(H24="","",H24-H23) -> 205736 | I25: =IF(I24="","",I24-I23) -> 293172 | J25: =IF(J24="","",J24-J23) -> 288358 | ... N25: =IF(N24="","",N24-N23)
A26: General & Administrative | B26: Budget | C26: =SUMIFS(Data!$D$2:$D$148,Data!$A$2:$A$148,"2026-01",Data!$B$2:$B$148,"Budget",Data!$C$2:$C$148,"General & Administrative") -> -4395523 | D26: =SUMIFS(Data!$D$2:$D$148,Data!$A$2:$A$148,"2026-02",Data!$B$2:$B$148,"Budget",Data!$C$2:$C$148,"General & Administrative") -> -4368557 | E26: =SUMIFS(Data!$D$2:$D$148,Data!$A$2:$A$148,"2026-03",Data!$B$2:$B$148,"Budget",Data!$C$2:$C$148,"General & Administrative") -> -4433276 | F26: =SUMIFS(Data!$D$2:$D$148,Data!$A$2:$A$148,"2026-04",Data!$B$2:$B$148,"Budget",Data!$C$2:$C$148,"General & Administrative") -> -4465636 | G26: =SUMIFS(Data!$D$2:$D$148,Data!$A$2:$A$148,"2026-05",Data!$B$2:$B$148,"Budget",Data!$C$2:$C$148,"General & Administrative") -> -4503389 | H26: =SUMIFS(Data!$D$2:$D$148,Data!$A$2:$A$148,"2026-06",Data!$B$2:$B$148,"Budget",Data!$C$2:$C$148,"General & Administrative") -> -4530355 | I26: =SUMIFS(Data!$D$2:$D$148,Data!$A$2:$A$148,"2026-07",Data!$B$2:$B$148,"Budget",Data!$C$2:$C$148,"General & Administrative") -> -4519569 | J26: =SUMIFS(Data!$D$2:$D$148,Data!$A$2:$A$148,"2026-08",Data!$B$2:$B$148,"Budget",Data!$C$2:$C$148,"General & Administrative") -> -4487209 | K26: =SUMIFS(Data!$D$2:$D$148,Data!$A$2:$A$148,"2026-09",Data!$B$2:$B$148,"Budget",Data!$C$2:$C$148,"General & Administrative") -> -4449456 | L26: =SUMIFS(Data!$D$2:$D$148,Data!$A$2:$A$148,"2026-10",Data!$B$2:$B$148,"Budget",Data!$C$2:$C$148,"General & Administrative") -> -4476422 | M26: =SUMIFS(Data!$D$2:$D$148,Data!$A$2:$A$148,"2026-11",Data!$B$2:$B$148,"Budget",Data!$C$2:$C$148,"General & Administrative") -> -4611254 | N26: =SUMIFS(Data!$D$2:$D$148,Data!$A$2:$A$148,"2026-12",Data!$B$2:$B$148,"Budget",Data!$C$2:$C$148,"General & Administrative") -> -4692154 | O26: =SUM(C26:K26) -> -40152970 | P26: =SUM(C27:K27) -> -40704328 | Q26: =P26-O26 -> -551358 | R26: =IF(O26=0,0,Q26/ABS(O26)) -> -0.013731438 | S26: =SUM(C26:N26) -> -53932800 | T26: =P26+SUM(Forecast!B12:D12) -> -54165856 | U26: =T26-S26 -> -233055.67
B27: Actual | C27: =SUMIFS(Data!$D$2:$D$148,Data!$A$2:$A$148,"2026-01",Data!$B$2:$B$148,"Actual",Data!$C$2:$C$148,"General & Administrative") -> -4543145 | D27: =SUMIFS(Data!$D$2:$D$148,Data!$A$2:$A$148,"2026-02",Data!$B$2:$B$148,"Actual",Data!$C$2:$C$148,"General & Administrative") -> -4386297 | E27: =SUMIFS(Data!$D$2:$D$148,Data!$A$2:$A$148,"2026-03",Data!$B$2:$B$148,"Actual",Data!$C$2:$C$148,"General & Administrative") -> -4360422 | F27: =SUMIFS(Data!$D$2:$D$148,Data!$A$2:$A$148,"2026-04",Data!$B$2:$B$148,"Actual",Data!$C$2:$C$148,"General & Administrative") -> -4519544 | G27: =SUMIFS(Data!$D$2:$D$148,Data!$A$2:$A$148,"2026-05",Data!$B$2:$B$148,"Actual",Data!$C$2:$C$148,"General & Administrative") -> -4461405 | H27: =SUMIFS(Data!$D$2:$D$148,Data!$A$2:$A$148,"2026-06",Data!$B$2:$B$148,"Actual",Data!$C$2:$C$148,"General & Administrative") -> -4587308 | I27: =SUMIFS(Data!$D$2:$D$148,Data!$A$2:$A$148,"2026-07",Data!$B$2:$B$148,"Actual",Data!$C$2:$C$148,"General & Administrative") -> -4651829 | J27: =SUMIFS(Data!$D$2:$D$148,Data!$A$2:$A$148,"2026-08",Data!$B$2:$B$148,"Actual",Data!$C$2:$C$148,"General & Administrative") -> -4632631 | K27: =SUMIFS(Data!$D$2:$D$148,Data!$A$2:$A$148,"2026-09",Data!$B$2:$B$148,"Actual",Data!$C$2:$C$148,"General & Administrative") -> -4561747
B28: Variance $ | C28: =IF(C27="","",C27-C26) -> -147622 | D28: =IF(D27="","",D27-D26) -> -17740 | E28: =IF(E27="","",E27-E26) -> 72854 | F28: =IF(F27="","",F27-F26) -> -53908 | G28: =IF(G27="","",G27-G26) -> 41984 | H28: =IF(H27="","",H27-H26) -> -56953 | I28: =IF(I27="","",I27-I26) -> -132260 | J28: =IF(J27="","",J27-J26) -> -145422 | ... N28: =IF(N27="","",N27-N26)
A29: Operating Income | B29: Budget | C29: =C11+C14+C17+C20+C23+C26 -> 2926415 | D29: =D11+D14+D17+D20+D23+D26 -> 1273039 | E29: =E11+E14+E17+E20+E23+E26 -> 5241147 | F29: =F11+F14+F17+F20+F23+F26 -> 7225194 | G29: =G11+G14+G17+G20+G23+G26 -> 9539927 | H29: =H11+H14+H17+H20+H23+H26 -> 11193304 | I29: =I11+I14+I17+I20+I23+I26 -> 10531951 | J29: =J11+J14+J17+J20+J23+J26 -> 8547900 | ... N29: =N11+N14+N17+N20+N23+N26 -> 21113569 | O29: =SUM(C29:K29) -> 62712048 | P29: =SUM(C30:K30) -> 70158084 | Q29: =P29-O29 -> 7446036 | R29: =IF(O29=0,0,Q29/ABS(O29)) -> 0.11873374 | S29: =SUM(C29:N29) -> 107865601 | T29: =P29+SUM(Forecast!B14:D14) -> 1.2252265e+08 | U29: =T29-S29 -> 14657052
B30: Actual | C30: =C12+C15+C18+C21+C24+C27 -> 2590036 | D30: =D12+D15+D18+D21+D24+D27 -> 1650334 | E30: =E12+E15+E18+E21+E24+E27 -> 5752912 | F30: =F12+F15+F18+F21+F24+F27 -> 7894265 | G30: =G12+G15+G18+G21+G24+G27 -> 11339696 | H30: =H12+H15+H18+H21+H24+H27 -> 12372955 | I30: =I12+I15+I18+I21+I24+I27 -> 11557934 | J30: =J12+J15+J18+J21+J24+J27 -> 9134498 | K30: =K12+K15+K18+K21+K24+K27 -> 7865454
B31: Variance $ | C31: =IF(C30="","",C30-C29) -> -336379 | D31: =IF(D30="","",D30-D29) -> 377295 | E31: =IF(E30="","",E30-E29) -> 511765 | F31: =IF(F30="","",F30-F29) -> 669071 | G31: =IF(G30="","",G30-G29) -> 1799769 | H31: =IF(H30="","",H30-H29) -> 1179651 | I31: =IF(I30="","",I30-I29) -> 1025983 | J31: =IF(J30="","",J30-J29) -> 586598 | ... N31: =IF(N30="","",N30-N29)

Sheet Forecast
A1: Rolling forecast, Oct 2026 - Sep 2027 ($000s)
A2: ="Scenario: "&Assumptions!B3 -> Scenario: Base
A4: Line item | B4: 2026-10 | C4: 2026-11 | D4: 2026-12 | E4: 2027-01 | F4: 2027-02 | G4: 2027-03 | H4: 2027-04 | I4: 2027-05 | J4: 2027-06 | K4: 2027-07 | L4: 2027-08 | M4: 2027-09 | N4: 12-mo total
A5: Revenue | B5: =Data!$G$2*Assumptions!$B$10 -> 112395510 | C5: =Data!$G$3*Assumptions!$B$10 -> 149730186 | D5: =Data!$G$4*Assumptions!$B$10 -> 173779417 | E5: =Data!$G$5*Assumptions!$B$10 -> 92922171 | F5: =Data!$G$6*Assumptions!$B$10 -> 86581544 | G5: =Data!$G$7*Assumptions!$B$10 -> 104542391 | H5: =Data!$G$8*Assumptions!$B$10 -> 114961469 | I5: =Data!$G$9*Assumptions!$B$10 -> 126619163 | J5: =Data!$G$10*Assumptions!$B$10 -> 134037068 | K5: =Data!$G$11*Assumptions!$B$10 -> 131622563 | L5: =Data!$G$12*Assumptions!$B$10 -> 122513825 | M5: =Data!$G$13*Assumptions!$B$10 -> 114465127 | N5: =SUM(B5:M5) -> 1464170434
A6: Cost of Goods Sold | B6: =-B5*(1-(Assumptions!$B$12+Assumptions!$B$11)) -> -70025952 | C6: =-C5*(1-(Assumptions!$B$12+Assumptions!$B$11)) -> -93286634 | D6: =-D5*(1-(Assumptions!$B$12+Assumptions!$B$11)) -> -1.0827006e+08 | E6: =-E5*(1-(Assumptions!$B$12+Assumptions!$B$11)) -> -57893447 | F6: =-F5*(1-(Assumptions!$B$12+Assumptions!$B$11)) -> -53943036 | G6: =-G5*(1-(Assumptions!$B$12+Assumptions!$B$11)) -> -65133211 | H6: =-H5*(1-(Assumptions!$B$12+Assumptions!$B$11)) -> -71624626 | I6: =-I5*(1-(Assumptions!$B$12+Assumptions!$B$11)) -> -78887737 | ... M6: =-M5*(1-(Assumptions!$B$12+Assumptions!$B$11)) -> -71315389 | N6: =SUM(B6:M6) -> -9.1222442e+08
A7: Gross Profit | B7: =B5+B6 -> 42369558 | C7: =C5+C6 -> 56443552 | D7: =D5+D6 -> 65509352 | E7: =E5+E6 -> 35028724 | F7: =F5+F6 -> 32638508 | G7: =G5+G6 -> 39409180 | H7: =H5+H6 -> 43336843 | I7: =I5+I6 -> 47731426 | ... M7: =M5+M6 -> 43149738 | N7: =SUM(B7:M7) -> 5.5194602e+08
A8: Store Operations | B8: =-(Assumptions!$B$15+Assumptions!$C$15*B$5) -> -15516507 | C8: =-(Assumptions!$B$15+Assumptions!$C$15*C$5) -> -17459248 | D8: =-(Assumptions!$B$15+Assumptions!$C$15*D$5) -> -18710670 | E8: =-(Assumptions!$B$15+Assumptions!$C$15*E$5) -> -14503195 | F8: =-(Assumptions!$B$15+Assumptions!$C$15*F$5) -> -14173255 | G8: =-(Assumptions!$B$15+Assumptions!$C$15*G$5) -> -15107863 | H8: =-(Assumptions!$B$15+Assumptions!$C$15*H$5) -> -15650029 | I8: =-(Assumptions!$B$15+Assumptions!$C$15*I$5) -> -16256646 | ... M8: =-(Assumptions!$B$15+Assumptions!$C$15*M$5) -> -15624201 | N8: =SUM(B8:M8) -> -1.9220428e+08
A9: Marketing | B9: =-(Assumptions!$B$16+Assumptions!$C$16*B$5) -> -5018381.2 | C9: =-(Assumptions!$B$16+Assumptions!$C$16*C$5) -> -6332272.1 | D9: =-(Assumptions!$B$16+Assumptions!$C$16*D$5) -> -7178618.4 | E9: =-(Assumptions!$B$16+Assumptions!$C$16*E$5) -> -4333070.8 | F9: =-(Assumptions!$B$16+Assumptions!$C$16*F$5) -> -4109929.9 | G9: =-(Assumptions!$B$16+Assumptions!$C$16*G$5) -> -4742012.4 | H9: =-(Assumptions!$B$16+Assumptions!$C$16*H$5) -> -5108683 | I9: =-(Assumptions!$B$16+Assumptions!$C$16*I$5) -> -5518943.4 | ... M9: =-(Assumptions!$B$16+Assumptions!$C$16*M$5) -> -5091215.7 | N9: =SUM(B9:M9) -> -64282615
A10: Supply Chain & Logistics | B10: =-(Assumptions!$B$17+Assumptions!$C$17*B$5) -> -5585151.1 | C10: =-(Assumptions!$B$17+Assumptions!$C$17*C$5) -> -6809415.3 | D10: =-(Assumptions!$B$17+Assumptions!$C$17*D$5) -> -7598028.3 | E10: =-(Assumptions!$B$17+Assumptions!$C$17*E$5) -> -4946589 | F10: =-(Assumptions!$B$17+Assumptions!$C$17*F$5) -> -4738669.6 | G10: =-(Assumptions!$B$17+Assumptions!$C$17*G$5) -> -5327634.7 | H10: =-(Assumptions!$B$17+Assumptions!$C$17*H$5) -> -5669293.1 | I10: =-(Assumptions!$B$17+Assumptions!$C$17*I$5) -> -6051567.6 | ... M10: =-(Assumptions!$B$17+Assumptions!$C$17*M$5) -> -5653017.2 | N10: =SUM(B10:M10) -> -70806763
A11: Technology | B11: =-(Assumptions!$B$18+Assumptions!$C$18*B$5) -> -2526148.2 | C11: =-(Assumptions!$B$18+Assumptions!$C$18*C$5) -> -2794525.1 | D11: =-(Assumptions!$B$18+Assumptions!$C$18*D$5) -> -2967400.9 | E11: =-(Assumptions!$B$18+Assumptions!$C$18*E$5) -> -2386165.8 | F11: =-(Assumptions!$B$18+Assumptions!$C$18*F$5) -> -2340586.8 | G11: =-(Assumptions!$B$18+Assumptions!$C$18*G$5) -> -2469696.7 | H11: =-(Assumptions!$B$18+Assumptions!$C$18*H$5) -> -2544593.3 | I11: =-(Assumptions!$B$18+Assumptions!$C$18*I$5) -> -2628393.6 | ... M11: =-(Assumptions!$B$18+Assumptions!$C$18*M$5) -> -2541025.4 | N11: =SUM(B11:M11) -> -31143495
A12: General & Administrative | B12: =-(Assumptions!$B$19+Assumptions!$C$19*B$5) -> -4476753.5 | C12: =-(Assumptions!$B$19+Assumptions!$C$19*C$5) -> -4488578.5 | D12: =-(Assumptions!$B$19+Assumptions!$C$19*D$5) -> -4496195.6 | E12: =-(Assumptions!$B$19+Assumptions!$C$19*E$5) -> -4470585.7 | F12: =-(Assumptions!$B$19+Assumptions!$C$19*F$5) -> -4468577.5 | G12: =-(Assumptions!$B$19+Assumptions!$C$19*G$5) -> -4474266.2 | H12: =-(Assumptions!$B$19+Assumptions!$C$19*H$5) -> -4477566.2 | I12: =-(Assumptions!$B$19+Assumptions!$C$19*I$5) -> -4481258.6 | ... M12: =-(Assumptions!$B$19+Assumptions!$C$19*M$5) -> -4477409 | N12: =SUM(B12:M12) -> -53757600
A13: Total Opex | B13: =SUM(B8:B12) -> -33122941 | C13: =SUM(C8:C12) -> -37884039 | D13: =SUM(D8:D12) -> -40950913 | E13: =SUM(E8:E12) -> -30639607 | F13: =SUM(F8:F12) -> -29831019 | G13: =SUM(G8:G12) -> -32121473 | H13: =SUM(H8:H12) -> -33450164 | I13: =SUM(I8:I12) -> -34936810 | ... M13: =SUM(M8:M12) -> -33386868 | N13: =SUM(B13:M13) -> -4.1219476e+08
A14: Operating Income | B14: =B7+B13 -> 9246617.1 | C14: =C7+C13 -> 18559513 | D14: =D7+D13 -> 24558439 | E14: =E7+E13 -> 4389117.5 | F14: =F7+F13 -> 2807488.7 | G14: =G7+G13 -> 7287706.9 | H14: =H7+H13 -> 9886679.1 | I14: =I7+I13 -> 12794616 | ... M14: =M7+M13 -> 9762869.8 | N14: =SUM(B14:M14) -> 1.3975126e+08
A15: Operating margin % | B15: =IF(B5=0,0,B14/B5) -> 0.082268563 | C15: =IF(C5=0,0,C14/C5) -> 0.12395305 | D15: =IF(D5=0,0,D14/D5) -> 0.14131961 | E15: =IF(E5=0,0,E14/E5) -> 0.047234341 | F15: =IF(F5=0,0,F14/F5) -> 0.032425949 | G15: =IF(G5=0,0,G14/G5) -> 0.069710543 | H15: =IF(H5=0,0,H14/H5) -> 0.085999937 | I15: =IF(I5=0,0,I14/I5) -> 0.10104802 | ... N15: =IF(N5=0,0,N14/N5) -> 0.095447399
